sprockets_statsd/__init__.py
sprockets_statsd/py.typed
sprockets_statsd/statsd.py
sprockets_statsd/tornado.py
sprockets_statsd-1.0.0.dist-info/LICENSE
sprockets_statsd-1.0.0.dist-info/METADATA
sprockets_statsd-1.0.0.dist-info/WHEEL
sprockets_statsd-1.0.0.dist-info/top_level.txt
sprockets_statsd-1.0.0.dist-info/RECORD
