Metadata-Version: 2.1
Name: sprockets-statsd
Version: 1.0.0
Summary: Asynchronously send metrics to a statsd instance.
Home-page: https://sprockets-statsd.readthedocs.io/
Author: Dave Shawley
Author-email: daveshawley@gmail.com
License: BSD 3-Clause License
Project-URL: Bug Tracker, https://github.com/sprockets/sprockets-statsd/issues/
Project-URL: Documentation, https://sprockets-statsd.readthedocs.io/
Project-URL: Source Code, https://github.com/sprockets/sprockets-statsd/
Platform: UNKNOWN
Classifier: Development Status :: 5 - Production/Stable
Classifier: Intended Audience :: Developers
Classifier: License :: OSI Approved :: BSD License
Classifier: Natural Language :: English
Classifier: Operating System :: OS Independent
Classifier: Programming Language :: Python :: 3
Classifier: Programming Language :: Python :: 3 :: Only
Classifier: Programming Language :: Python :: 3.7
Classifier: Programming Language :: Python :: 3.9
Classifier: Programming Language :: Python :: 3.10
Classifier: Topic :: Communications
Classifier: Topic :: Internet
Classifier: Topic :: Software Development
Classifier: Typing :: Typed
License-File: LICENSE
Provides-Extra: dev
Requires-Dist: asynctest (==0.13.0) ; extra == 'dev'
Requires-Dist: coverage (==5.5) ; extra == 'dev'
Requires-Dist: flake8 (==3.9.2) ; extra == 'dev'
Requires-Dist: flake8-import-order (==0.18.1) ; extra == 'dev'
Requires-Dist: sphinx (==4.1.1) ; extra == 'dev'
Requires-Dist: sphinx-autodoc-typehints (==1.12.0) ; extra == 'dev'
Requires-Dist: sprockets.http (==2.2.0) ; extra == 'dev'
Requires-Dist: tornado (>=5) ; extra == 'dev'
Requires-Dist: yapf (==0.31.0) ; extra == 'dev'
Provides-Extra: readthedocs
Requires-Dist: sphinx (==4.1.1) ; extra == 'readthedocs'
Requires-Dist: sphinx-autodoc-typehints (==1.12.1) ; extra == 'readthedocs'
Requires-Dist: tornado (>=5) ; extra == 'readthedocs'
Provides-Extra: tornado
Requires-Dist: tornado (>=5) ; extra == 'tornado'
